fnmatch2/__init__.py
fnmatch2/fnmatch2.py
fnmatch2-0.0.8.dist-info/DESCRIPTION.rst
fnmatch2-0.0.8.dist-info/METADATA
fnmatch2-0.0.8.dist-info/RECORD
fnmatch2-0.0.8.dist-info/WHEEL
fnmatch2-0.0.8.dist-info/metadata.json
fnmatch2-0.0.8.dist-info/top_level.txt
